tree_shaking/__init__.py
tree_shaking/__main__.py
tree_shaking/_cache/auxiliary/readme.md
tree_shaking/_cache/dumped_resources_maps/.gitkeep
tree_shaking/_cache/ignores.txt
tree_shaking/_cache/module_graphs/.gitkeep
tree_shaking/_rooms/.gitkeep
tree_shaking/cache.py
tree_shaking/config.py
tree_shaking/export.py
tree_shaking/file_parser.py
tree_shaking/finder.py
tree_shaking/graph.py
tree_shaking/insight.py
tree_shaking/module.py
tree_shaking/patch.py
tree_shaking/patches/implicit_import_hooks.yaml
tree_shaking/patches/optional_import_list.yaml
tree_shaking/path_scope.py
tree_shaking/pyinstaller_hooks.py
tree_shaking/ui.py
tree_shaking-0.2.3.dist-info/METADATA
tree_shaking-0.2.3.dist-info/WHEEL
tree_shaking-0.2.3.dist-info/RECORD
