Metadata-Version: 2.3
Name: tree-shaking
Version: 0.2.3
Summary: Python tree-shaking for dependencies to reduce the size of packaging.
Author: Likianta
Author-email: likianta@foxmail.com
Requires-Python: >=3.12
Classifier: Programming Language :: Python :: 3
Classifier: Programming Language :: Python :: 3.12
Classifier: Programming Language :: Python :: 3.13
Provides-Extra: ui
Requires-Dist: argsense (>=1.1.0,<2.0.0)
Requires-Dist: lk-utils (>=3.4.0,<4.0.0)
Requires-Dist: streamlit ; extra == "ui"
Requires-Dist: streamlit-canary ; extra == "ui"
Project-URL: Homepage, https://github.com/likianta/python-tree-shaking
